watbot/__init__.py
watbot/cli.py
watbot/config.py
watbot/gemini_bot.py
watbot/insta_bot.py
watbot/instagram_bot.py
watbot/session_gemini_bot.py
watbot/start.py
watbot/test_watbot.py
watbot/whatsapp_bot.py
watbot-0.1.1.dist-info/licenses/LICENSE
watbot-0.1.1.dist-info/METADATA
watbot-0.1.1.dist-info/WHEEL
watbot-0.1.1.dist-info/entry_points.txt
watbot-0.1.1.dist-info/top_level.txt
watbot-0.1.1.dist-info/RECORD
