Metadata-Version: 2.4
Name: watbot
Version: 0.1.1
Summary: WhatsApp & Instagram Automation Bot with AI-powered responses
Home-page: https://github.com/nithin434/woat
Author: Nithin Jambula
Author-email: nithin@example.com
Project-URL: Bug Tracker, https://github.com/nithin434/woat/issues
Project-URL: Documentation, https://github.com/nithin434/woat/wiki
Project-URL: Source Code, https://github.com/nithin434/woat
Keywords: whatsapp,instagram,bot,automation,ai,chat,messaging,api
Classifier: Development Status :: 4 - Beta
Classifier: Environment :: Web Environment
Classifier: Framework :: AsyncIO
Classifier: Intended Audience :: Developers
Classifier: License :: OSI Approved :: MIT License
Classifier: Operating System :: OS Independent
Classifier: Programming Language :: Python
Classifier: Programming Language :: Python :: 3 :: Only
Classifier: Programming Language :: Python :: 3.8
Classifier: Programming Language :: Python :: 3.9
Classifier: Programming Language :: Python :: 3.10
Classifier: Programming Language :: Python :: 3.11
Classifier: Topic :: Communications :: Chat
Classifier: Topic :: Internet :: WWW/HTTP :: Dynamic Content
Classifier: Topic :: Software Development :: Libraries :: Python Modules
Classifier: Typing :: Typed
Requires-Python: >=3.8
License-File: LICENSE
Requires-Dist: playwright>=1.40.0
Requires-Dist: python-dotenv>=1.0.0
Requires-Dist: requests>=2.31.0
Requires-Dist: fastapi>=0.104.1
Requires-Dist: uvicorn>=0.24.0
Requires-Dist: pydantic>=2.4.2
Requires-Dist: google-generativeai>=0.3.0
Requires-Dist: aiohttp>=3.9.0
Requires-Dist: aiosmtplib>=2.0.2
Requires-Dist: python-multipart>=0.0.6
Requires-Dist: pytest>=7.0
Requires-Dist: pytest-cov>=3.0
Requires-Dist: pytest-asyncio>=0.21.1
Requires-Dist: black>=22.0
Requires-Dist: flake8>=4.0
Requires-Dist: mypy>=0.950
Requires-Dist: build>=1.0.3
Requires-Dist: twine>=4.0.2
Provides-Extra: dev
Requires-Dist: pytest>=7.0; extra == "dev"
Requires-Dist: pytest-asyncio>=0.21.1; extra == "dev"
Requires-Dist: pytest-cov>=3.0; extra == "dev"
Requires-Dist: black>=22.0; extra == "dev"
Requires-Dist: flake8>=4.0; extra == "dev"
Requires-Dist: mypy>=0.950; extra == "dev"
Dynamic: author
Dynamic: author-email
Dynamic: classifier
Dynamic: description
Dynamic: description-content-type
Dynamic: home-page
Dynamic: keywords
Dynamic: license-file
Dynamic: project-url
Dynamic: provides-extra
Dynamic: requires-dist
Dynamic: requires-python
Dynamic: summary
